providers/__init__.py
providers/hsm.py
providers/mobile.py
providers/tee.py
providers/tpm.py
tenzro_trust-0.1.0.dist-info/LICENSE
tenzro_trust-0.1.0.dist-info/METADATA
tenzro_trust-0.1.0.dist-info/WHEEL
tenzro_trust-0.1.0.dist-info/top_level.txt
tenzro_trust-0.1.0.dist-info/RECORD
