Metadata-Version: 2.2
Name: tenzro-trust
Version: 0.1.0
Summary: A flexible, extensible hardware-rooted trust framework for distributed ledger systems
Home-page: https://github.com/tenzro/tenzro-trust
Author: Hilal Agil
Author-email: Hilal Agil <hilaal@gmail.com>
License: MIT
Project-URL: Homepage, https://github.com/tenzro/tenzro-trust
Project-URL: Bug Tracker, https://github.com/tenzro/tenzro-trust/issues
Project-URL: Documentation, https://github.com/tenzro/tenzro-trust#readme
Keywords: security,trust,hsm,tpm,tee,distributed-ledger
Classifier: Development Status :: 4 - Beta
Classifier: Intended Audience :: Developers
Classifier: License :: OSI Approved :: MIT License
Classifier: Programming Language :: Python :: 3
Classifier: Programming Language :: Python :: 3.9
Classifier: Programming Language :: Python :: 3.10
Classifier: Programming Language :: Python :: 3.11
Classifier: Topic :: Security :: Cryptography
Classifier: Topic :: Software Development :: Libraries :: Python Modules
Requires-Python: >=3.9
License-File: LICENSE
Requires-Dist: cryptography>=3.4.0
Requires-Dist: pycryptodome>=3.10.0
Dynamic: author
Dynamic: home-page
Dynamic: requires-python
